setup.py
distributions/__init__.py
vidit_distribution.egg-info/PKG-INFO
vidit_distribution.egg-info/SOURCES.txt
vidit_distribution.egg-info/dependency_links.txt
vidit_distribution.egg-info/not-zip-safe
vidit_distribution.egg-info/top_level.txt