Metadata-Version: 1.0
Name: vidit-distribution
Version: 0.3
Summary: Gaussian distributions
Home-page: UNKNOWN
Author: Vidit Kumar Jain
Author-email: viditjain0025@gmail.com
License: UNKNOWN
Platform: UNKNOWN
